Takamol/Calculation.py
Takamol/__init__.py
Takamol_Custom_Library-0.2.dist-info/LICENSE.rst
Takamol_Custom_Library-0.2.dist-info/METADATA
Takamol_Custom_Library-0.2.dist-info/WHEEL
Takamol_Custom_Library-0.2.dist-info/top_level.txt
Takamol_Custom_Library-0.2.dist-info/RECORD
