Metadata-Version: 2.1
Name: Takamol-Custom-Library
Version: 0.2
Summary: Takamol Custom Library
Home-page: 
Author: Haitham Al-Mughrabi
Author-email: Haitham Al-Mughrabi <haitham.almughrabi@wareefunited.com>
Keywords: Takamol Custom Library
Classifier: Programming Language :: Python :: 3
Classifier: License :: OSI Approved :: MIT License
Classifier: Operating System :: OS Independent
Requires-Python: >=3.6
License-File: LICENSE.rst
Requires-Dist: selenium
Requires-Dist: webdriver-manager
